README.rst
setup.py
audit/__init__.py
audit/schemas.py
audit/models/__init__.py
audit/models/core.py
audit/models/mixins.py
audit/models/utils.py
audit/utils/__init__.py
audit/utils/sqlalchemy.py
audit_utils.egg-info/PKG-INFO
audit_utils.egg-info/SOURCES.txt
audit_utils.egg-info/dependency_links.txt
audit_utils.egg-info/requires.txt
audit_utils.egg-info/top_level.txt