Metadata-Version: 1.2
Name: audit-utils
Version: 0.1.1
Summary: DB Table Auditing Utilities
Home-page: https://github.com/fictivekin/audit-utils
Author: Fictive Kin LLC
Author-email: hello@fictivekin.com
Maintainer: Fictive Kin LLC
Maintainer-email: hello@fictivekin.com
License: MIT
Platform: UNKNOWN
Classifier: Development Status :: 3 - Alpha
Classifier: License :: OSI Approved :: MIT License
Classifier: Programming Language :: Python :: 3.8
Classifier: Topic :: Software Development
Requires-Python: >=3.8
